anadaptor/__init__.py
anadaptor/main.py
anadaptor-0.0.1.dist-info/DESCRIPTION.rst
anadaptor-0.0.1.dist-info/METADATA
anadaptor-0.0.1.dist-info/RECORD
anadaptor-0.0.1.dist-info/WHEEL
anadaptor-0.0.1.dist-info/entry_points.txt
anadaptor-0.0.1.dist-info/metadata.json
anadaptor-0.0.1.dist-info/top_level.txt
