Metadata-Version: 2.0
Name: anadaptor
Version: 0.0.1
Summary: No path vars no problem.
Home-page: https://github.com/draperjames/anadaptor
Author: James Draper
Author-email: james.draper@duke.edu
License: MIT
Keywords: anadaptor
Platform: UNKNOWN
Classifier: Development Status :: 3 - Alpha
Classifier: Intended Audience :: Developers
Classifier: Topic :: Software Development :: Build Tools
Classifier: License :: OSI Approved :: MIT License
Classifier: Programming Language :: Python :: 3.5
Classifier: Programming Language :: Python :: 3.6
